goulib/__init__.py
goulib/cie-cmf.txt
goulib/colors.csv
goulib/colors.py
goulib/containers.py
goulib/datetime2.py
goulib/decorators.py
goulib/drawing.py
goulib/expr.py
goulib/geom.py
goulib/geom3d.py
goulib/graph.py
goulib/image.py
goulib/interval.py
goulib/itertools2.py
goulib/markup.py
goulib/math2.py
goulib/motion.py
goulib/notebook.py
goulib/optim.py
goulib/periodic.py
goulib/piecewise.py
goulib/plot.py
goulib/polynomial.py
goulib/stats.py
goulib/table.py
goulib/tests.py
goulib/units.py
goulib/workdays.py
goulib-3.0.0.dist-info/LICENSE.TXT
goulib-3.0.0.dist-info/METADATA
goulib-3.0.0.dist-info/WHEEL
goulib-3.0.0.dist-info/top_level.txt
goulib-3.0.0.dist-info/RECORD
