Metadata-Version: 2.2
Name: goulib
Version: 3.0.0
Summary: library of useful Python code for scientific + technical applications
Author-email: Philippe Guglielmetti <goulib@goulu.net>
License:                    GNU LESSER GENERAL PUBLIC LICENSE
Keywords: math,geometry,graph,optimization,drawing
Classifier: Development Status :: 5 - Production/Stable
Classifier: Environment :: Console
Classifier: Intended Audience :: Developers
Classifier: License :: OSI Approved :: GNU Library or Lesser General Public License (LGPL)
Classifier: Operating System :: OS Independent
Classifier: Programming Language :: Python
Classifier: Programming Language :: Python :: 3.9
Classifier: Topic :: Scientific/Engineering
Classifier: Topic :: Software Development :: Libraries :: Python Modules
Classifier: Topic :: Multimedia :: Graphics :: Graphics Conversion
Requires-Python: >=3.9
License-File: LICENSE.TXT
Requires-Dist: networkx
Requires-Dist: numpy
Requires-Dist: scikit-image
Requires-Dist: scipy
Requires-Dist: pydot
Requires-Dist: pydotplus
Requires-Dist: graphviz
Requires-Dist: ipython
Requires-Dist: lxml
Requires-Dist: xlrd
Requires-Dist: xlsxwriter
Requires-Dist: dxfgrabber
Requires-Dist: dxfwrite
Requires-Dist: svg.path
Requires-Dist: tinycss
Requires-Dist: pdfminer
Requires-Dist: sortedcollections
Requires-Dist: bitarray
Requires-Dist: pint
Requires-Dist: pillow
Requires-Dist: matplotlib
Provides-Extra: dev
Requires-Dist: sphinx; extra == "dev"
Requires-Dist: pytest; extra == "dev"
Requires-Dist: pytest-cov; extra == "dev"
